README.md
setup.cfg
setup.py
nili/Fuzzing.py
nili/MitM.py
nili/NetScan.py
nili/PortScan.py
nili/Reverse.py
nili/__init__.py
nili/__main__.py
nili.egg-info/PKG-INFO
nili.egg-info/SOURCES.txt
nili.egg-info/dependency_links.txt
nili.egg-info/entry_points.txt
nili.egg-info/top_level.txt