Metadata-Version: 1.1
Name: nili
Version: 0.1.1
Summary: Nili is a Tool for Network Scan, Man in the Middle, Protocol Reverse Engineering and Fuzzing.
Home-page: https://github.com/niloofarkheirkhah/nili
Author: Niloofar Kheirkhah - Ehsan Mir
Author-email: niloofar.kheirkhah@gmail.com - ehsan.mir@icloud.com
License: GPLv3
Download-URL: https://github.com/niloofarkheirkhah/nili/archive/0.1.1.zip
Keywords: Security Test
Platform: UNKNOWN
Classifier: Topic :: Security
Classifier: License :: OSI Approved :: GNU General Public License v3 (GPLv3)
